odoo10_addon_l10n_es_aeat_mod303-10.0.4.2.0-py3.8-nspkg.pth
odoo/addons/l10n_es_aeat_mod303/README.rst
odoo/addons/l10n_es_aeat_mod303/__init__.py
odoo/addons/l10n_es_aeat_mod303/__manifest__.py
odoo/addons/l10n_es_aeat_mod303/data/aeat.model.export.config.csv
odoo/addons/l10n_es_aeat_mod303/data/aeat.model.export.config.line.csv
odoo/addons/l10n_es_aeat_mod303/data/aeat_export_mod303_2017_data.xml
odoo/addons/l10n_es_aeat_mod303/data/aeat_export_mod303_2018_data.xml
odoo/addons/l10n_es_aeat_mod303/data/aeat_export_mod303_2021_data.xml
odoo/addons/l10n_es_aeat_mod303/data/aeat_export_mod303_data.xml
odoo/addons/l10n_es_aeat_mod303/data/l10n.es.aeat.map.tax.csv
odoo/addons/l10n_es_aeat_mod303/data/l10n.es.aeat.map.tax.line.csv
odoo/addons/l10n_es_aeat_mod303/data/l10n_es_aeat_mod303_report_activity_code_data.xml
odoo/addons/l10n_es_aeat_mod303/data/tax_code_map_mod303_data.xml
odoo/addons/l10n_es_aeat_mod303/data/2022/aeat.model.export.config.csv
odoo/addons/l10n_es_aeat_mod303/data/2022/aeat.model.export.config.line.csv
odoo/addons/l10n_es_aeat_mod303/docs/303_register_design_e15v32.xlsx
odoo/addons/l10n_es_aeat_mod303/docs/DR303e15v34.xlsx
odoo/addons/l10n_es_aeat_mod303/docs/DR303e17v20_04.xlsx
odoo/addons/l10n_es_aeat_mod303/docs/DR303e18v10_00.xlsx
odoo/addons/l10n_es_aeat_mod303/docs/DR303e18v10_40.xlsx
odoo/addons/l10n_es_aeat_mod303/docs/DR303e21v100.xlsx
odoo/addons/l10n_es_aeat_mod303/docs/DR303e21v200.xlsx
odoo/addons/l10n_es_aeat_mod303/docs/DR303e22.xlsx
odoo/addons/l10n_es_aeat_mod303/i18n/bg.po
odoo/addons/l10n_es_aeat_mod303/i18n/ca.po
odoo/addons/l10n_es_aeat_mod303/i18n/cs.po
odoo/addons/l10n_es_aeat_mod303/i18n/de.po
odoo/addons/l10n_es_aeat_mod303/i18n/es.po
odoo/addons/l10n_es_aeat_mod303/i18n/es_CO.po
odoo/addons/l10n_es_aeat_mod303/i18n/es_CR.po
odoo/addons/l10n_es_aeat_mod303/i18n/es_ES.po
odoo/addons/l10n_es_aeat_mod303/i18n/eu.po
odoo/addons/l10n_es_aeat_mod303/i18n/fr.po
odoo/addons/l10n_es_aeat_mod303/i18n/gl.po
odoo10_addon_l10n_es_aeat_mod303-10.0.4.2.0.dist-info/METADATA
odoo10_addon_l10n_es_aeat_mod303-10.0.4.2.0.dist-info/WHEEL
odoo10_addon_l10n_es_aeat_mod303-10.0.4.2.0.dist-info/namespace_packages.txt
odoo10_addon_l10n_es_aeat_mod303-10.0.4.2.0.dist-info/top_level.txt
odoo10_addon_l10n_es_aeat_mod303-10.0.4.2.0.dist-info/RECORD
