Metadata-Version: 2.1
Name: odoo10-addon-l10n-es-aeat-mod303
Version: 10.0.4.2.0
Summary: AEAT modelo 303
Home-page: https://github.com/OCA/l10n-spain
Author: Guadaltech,AvanzOSC,Tecnativa,Eficent,Odoo Community Association (OCA)
Author-email: support@odoo-community.org
License: AGPL-3
Platform: UNKNOWN
Classifier: Programming Language :: Python
Classifier: Framework :: Odoo
Classifier: Framework :: Odoo :: 10.0
Classifier: License :: OSI Approved :: GNU Affero General Public License v3
Requires-Python: ~=2.7
Requires-Dist: odoo10-addon-l10n-es-aeat
Requires-Dist: odoo (<10.1dev,>=10.0)
